{
  "liang": {
    "failures": 1,
    "last_failure": "2026-03-14T03:05:58.595768+00:00"
  },
  "mycroft": {
    "failures": 1,
    "last_failure": "2026-03-14T03:06:00.487993+00:00"
  },
  "pearl": {
    "failures": 1,
    "last_failure": "2026-03-14T03:06:02.397950+00:00"
  },
  "pigliucci": {
    "failures": 1,
    "last_failure": "2026-03-14T03:06:04.422938+00:00"
  },
  "sabine": {
    "failures": 1,
    "last_failure": "2026-03-14T03:06:06.381273+00:00"
  },
  "scott": {
    "failures": 1,
    "last_failure": "2026-03-14T03:06:08.151010+00:00"
  },
  "wolfram": {
    "failures": 1,
    "last_failure": "2026-03-14T03:06:10.326889+00:00"
  }
}